{
  "main": {
    "id": "c10272800f1435fb",
    "type": "split",
    "children": [
      {
        "id": "55b6b348dbf9d301",
        "type": "tabs",
        "children": [
          {
            "id": "37a80e1d14d5d11a",
            "type": "leaf",
            "state": {
              "type": "graph",
              "state": {}
            }
          },
          {
            "id": "9bd3275253af9a8d",
            "type": "leaf",
            "state": {
              "type": "markdown",
              "state": {
                "file": "04 - Projects/wwt/en/Формат тест кейсів_en.md",
                "mode": "source",
                "source": false
              }
            }
          },
          {
            "id": "02384e69a15035bb",
            "type": "leaf",
            "state": {
              "type": "markdown",
              "state": {
                "file": "02 - Learning/courses/Learning how to learn/Як запам'ятовування пов'язанно зі сном.md",
                "mode": "source",
                "source": false
              }
            }
          }
        ]
      }
    ],
    "direction": "vertical"
  },
  "left": {
    "id": "832ac937b04b25d4",
    "type": "split",
    "children": [
      {
        "id": "d41df795cbf97ffd",
        "type": "tabs",
        "children": [
          {
            "id": "a24dc56c09266e71",
            "type": "leaf",
            "state": {
              "type": "file-explorer",
              "state": {
                "sortOrder": "alphabetical"
              }
            }
          },
          {
            "id": "f40408fcf46559a5",
            "type": "leaf",
            "state": {
              "type": "search",
              "state": {
                "query": "tag:#course",
                "matchingCase": false,
                "explainSearch": false,
                "collapseAll": false,
                "extraContext": false,
                "sortOrder": "byCreatedTimeReverse"
              }
            }
          },
          {
            "id": "44f18f7607429721",
            "type": "leaf",
            "state": {
              "type": "bookmarks",
              "state": {}
            }
          }
        ],
        "currentTab": 1
      }
    ],
    "direction": "horizontal",
    "width": 343.5
  },
  "right": {
    "id": "2f506f9fee39b619",
    "type": "split",
    "children": [
      {
        "id": "0b14c0aa96eed29d",
        "type": "tabs",
        "children": [
          {
            "id": "2dc5deccf74b3c16",
            "type": "leaf",
            "state": {
              "type": "backlink",
              "state": {
                "collapseAll": false,
                "extraContext": false,
                "sortOrder": "alphabetical",
                "showSearch": false,
                "searchQuery": "",
                "backlinkCollapsed": false,
                "unlinkedCollapsed": true
              }
            }
          },
          {
            "id": "828c2782cd9de295",
            "type": "leaf",
            "state": {
              "type": "outgoing-link",
              "state": {
                "linksCollapsed": false,
                "unlinkedCollapsed": true
              }
            }
          },
          {
            "id": "ee4f8aa1c9d7400d",
            "type": "leaf",
            "state": {
              "type": "tag",
              "state": {
                "sortOrder": "frequency",
                "useHierarchy": true
              }
            }
          },
          {
            "id": "13e968e057a92b05",
            "type": "leaf",
            "state": {
              "type": "outline",
              "state": {}
            }
          },
          {
            "id": "3d545f4ee89dcaa5",
            "type": "leaf",
            "state": {
              "type": "advanced-tables-toolbar",
              "state": {}
            }
          },
          {
            "id": "80f923ded037f9d6",
            "type": "leaf",
            "state": {
              "type": "all-properties",
              "state": {
                "sortOrder": "frequency",
                "showSearch": false,
                "searchQuery": ""
              }
            }
          },
          {
            "id": "329727113b19eb13",
            "type": "leaf",
            "state": {
              "type": "empty",
              "state": {}
            }
          }
        ],
        "currentTab": 4
      }
    ],
    "direction": "horizontal",
    "width": 354.5
  },
  "left-ribbon": {
    "hiddenItems": {
      "switcher:Open quick switcher": false,
      "graph:Open graph view": false,
      "canvas:Create new canvas": false,
      "daily-notes:Open today's daily note": false,
      "templates:Insert template": false,
      "command-palette:Open command palette": false,
      "templater-obsidian:Templater": false,
      "obsidian-to-anki-plugin:Obsidian_to_Anki - Scan Vault": false,
      "table-editor-obsidian:Advanced Tables Toolbar": false
    }
  },
  "active": "37a80e1d14d5d11a",
  "lastOpenFiles": [
    "04 - Projects/wwt/en/Brevo_en.md",
    "02 - Learning/courses/Learning how to learn/Як запам'ятовування пов'язанно зі сном.md",
    "02 - Learning/courses/Linux LearnQuest/Basic Network Troubleshooting.md",
    "02 - Learning/courses/Linux LearnQuest/Command Line Network Configuration.md",
    "02 - Learning/courses/Linux LearnQuest/Network Configuration Files.md",
    "02 - Learning/courses/Learning how to learn/Використання Сфокусованого та Розсіяного режимів.md",
    "02 - Learning/courses/Learning how to learn/Вступ до Сфокусованого та Розсіяного режимів.md",
    "04 - Projects/wwt/Як працює fe+be.md",
    "04 - Projects/wwt/Формат тест кейсів.md",
    "04 - Projects/wwt/project-plan.md",
    "04 - Projects/wwt/Destination select.md",
    "04 - Projects/wwt/Bug report.md",
    "04 - Projects/wwt/Brevo.md",
    "04 - Projects/wwt/en/Формат тест кейсів_en.md",
    "04 - Projects/wwt/en/project-plan-en.md",
    "04 - Projects/wwt/en/How to test backend + frontend.md",
    "04 - Projects/wwt/en/Destination select_en.md",
    "04 - Projects/wwt/en/Bug report_en.md",
    "04 - Projects/wwt/images/Pasted image 20240510152317.png",
    "04 - Projects/wwt/images/Pasted image 20240510152341.png",
    "04 - Projects/wwt/images",
    "04 - Projects/wwt/en",
    "04 - Projects/wwt/Untitled 1.md",
    "04 - Projects/wwt/Git.md",
    "03 - Programming/base/big numbers/Довга арифметика.md",
    "03 - Programming/base/big numbers/images",
    "03 - Programming/base/big numbers/images/Pasted image 20240508214207.png",
    "03 - Programming/base/big numbers",
    "03 - Programming/base",
    "01 - Fast notes/Якщо чогось не розумієш - пиши книгу.md",
    "02 - Learning/courses/Learning how to learn/images/Pasted image 20240508211950.png",
    "02 - Learning/books/Hyperfocus/Hyperfocus.md",
    "02 - Learning/books/Hyperfocus/Intro.md",
    "03 - Programming/js/ydnjs/up & going.md",
    "03 - Programming/http/CORS.md",
    "02 - Learning/books/Power.pdf",
    "01 - Fast notes",
    "02 - Learning",
    "02 - Learning/courses/Linux LearnQuest/images/Pasted image 20230929214134.png",
    "02 - Learning/courses/Linux LearnQuest/images",
    "02 - Learning/courses/Linux LearnQuest/images/Pasted image 20231205090632.png",
    "02 - Learning/courses/Linux LearnQuest/images/Pasted image 20231205090419.png",
    "02 - Learning/courses/Linux LearnQuest/images/Pasted image 20231204084755.png",
    "02 - Learning/courses/Linux LearnQuest/images/Pasted image 20231204084614.png",
    "03 - Programming/algoritms/images/Pasted image 20230521123641.png",
    "03 - Programming/algoritms/images",
    "tmp/Untitled 1.canvas",
    "Untitled.canvas"
  ]
}